acquisition_extractor/__init__.py
acquisition_extractor/__main__.py
acquisition_extractor/decisions.py
acquisition_extractor/statute_parts/__init__.py
acquisition_extractor/statute_parts/body.py
acquisition_extractor/statute_parts/helpers.py
acquisition_extractor/statute_parts/meta.py
acquisition_extractor/statute_parts/partials.py
acquisition_extractor/statute_parts/title.py
acquisition_extractor/statutes.py
acquisition_extractor-0.3.4.dist-info/WHEEL
acquisition_extractor-0.3.4.dist-info/METADATA
acquisition_extractor-0.3.4.dist-info/RECORD
